eamcsv2json/__init__.py
eamcsv2json/__main__.py
eamcsv2json/dict2json.py
eamcsv2json/eamcsv2dict.py
eamcsv2json/randomdata.py
eamcsv2json/transform2dict.py
eamcsv2json-1.0.5.dist-info/METADATA
eamcsv2json-1.0.5.dist-info/RECORD
eamcsv2json-1.0.5.dist-info/WHEEL
eamcsv2json-1.0.5.dist-info/entry_points.txt
eamcsv2json-1.0.5.dist-info/top_level.txt
