Metadata-Version: 2.1
Name: eamcsv2json
Version: 1.0.5
Summary: Converts EAM CSV export to JSON
Home-page: https://github.com/crowdstrike/eamcsv2json
Author: Andrew Roden
Author-email: andrew.roden@crowdstrike.com
License: BSD
Platform: UNKNOWN
Classifier: Development Status :: 2 - Pre-Alpha
Classifier: Intended Audience :: Developers
Classifier: License :: OSI Approved :: BSD License
Classifier: Natural Language :: English
Classifier: Programming Language :: Python :: 2.7
Classifier: Programming Language :: Python :: 3.5
Classifier: Programming Language :: Python :: 3.6
Classifier: Programming Language :: Python :: 3.7
